{
  "plan_analysis": "Applying the simulated algorithm's fractional shares, single-slot compounding, and decoupled portfolio parameters to the live bot environment. The project plan will not be modified or marked completed as per the user's strict directives.",
  "summary": "Update live bot for fractional shares, single-slot compounding, and decoupled roster sizing.",
  "event_type": "feat",
  "commands": [
    {
      "command": "update_file",
      "path": "live/core/portfolio_manager.py",
      "content": "import pandas as pd\nfrom live.core.math_utils import get_friction, get_regime\n\nclass PortfolioManager:\n    def __init__(self, assets, active_roster_size=5):\n        self.assets = assets\n        self.active_roster_size = active_roster_size\n        self.golden_list = []\n        self.active_roster = []\n        \n        # Exact Backtest Parameters\n        self.draft_size = 30\n        self.max_sector_weight = 0.15\n        self.hedge_quota = 0.20\n        self.lookback_days = 30\n\n    def rebuild_golden_list(self, current_time, daily_master):\n        \"\"\"\n        MACRO FILTER: Runs Quarterly (every 13 weeks).\n        Averages the last 30 days of daily flux (f_d) and applies strict regime capping.\n        \"\"\"\n        print(f\"\\n[PORTFOLIO] {current_time.strftime('%Y-%m-%d')} - Rebuilding Quarterly Golden List...\")\n        screener_scores = {}\n        screen_start = current_time - pd.DateOffset(days=self.lookback_days)\n        \n        for t in self.assets:\n            df = daily_master.get(t)\n            if df is not None and not df.empty:\n                # Mask out future data to prevent lookahead bias\n                mask = (df.index >= screen_start) & (df.index < current_time)\n                screen_data = df[mask]\n                \n                # Require at least 50% of the lookback period to have valid data\n                if len(screen_data) > (self.lookback_days * 0.5):\n                    avg_flux = screen_data['f_d'].mean()\n                    screener_scores[t] = avg_flux * (1 - (get_friction(t) * 100))\n                else:\n                    screener_scores[t] = 0.0\n            else:\n                screener_scores[t] = 0.0\n                \n        sorted_tickers = sorted(screener_scores.keys(), key=lambda x: screener_scores[x], reverse=True)\n        \n        new_golden_list = []\n        regime_counts = {'Crypto': 0, 'Forex': 0, 'Commodities': 0, 'Defensive_Macro': 0, 'Equities': 0}\n        max_per_regime = int(self.draft_size * self.max_sector_weight)\n        hedge_slots = int(self.draft_size * self.hedge_quota)\n        \n        for t in sorted_tickers:\n            if len(new_golden_list) >= (self.draft_size - hedge_slots): \n                break\n            reg = get_regime(t)\n            if regime_counts[reg] < max_per_regime:\n                new_golden_list.append(t)\n                regime_counts[reg] += 1\n                \n        # Fill strictly designated hedge slots\n        if hedge_slots > 0:\n            defensive_candidates = [t for t in sorted_tickers if get_regime(t) == 'Defensive_Macro' and t not in new_golden_list]\n            for t in defensive_candidates:\n                if len(new_golden_list) >= self.draft_size: \n                    break\n                new_golden_list.append(t)\n        \n        self.golden_list = new_golden_list\n\n    def rebuild_active_roster(self, current_time, daily_master):\n        \"\"\"\n        MESO FILTER: Runs Weekly.\n        Drafts the Top candidates from the Golden List based on the immediate f_d score.\n        Applies a 1.15x modifier to incumbent assets to prevent whiplash.\n        \"\"\"\n        if not self.golden_list:\n            return\n\n        print(f\"[PORTFOLIO] {current_time.strftime('%Y-%m-%d')} - Drafting Weekly Active Roster...\")\n        scores = {}\n        \n        for t in self.golden_list:\n            df = daily_master.get(t)\n            # Mask out future data\n            past_df = df[df.index <= current_time] if df is not None else None\n            \n            if past_df is not None and not past_df.empty:\n                raw_flux = past_df['f_d'].iloc[-1]\n            else:\n                raw_flux = 0.0\n                \n            # Severe 100x friction penalty for daily sorting\n            score = raw_flux * (1 - (get_friction(t) * 100))\n            \n            # The Incumbent Modifier\n            if t in self.active_roster: \n                score *= 1.15\n                \n            scores[t] = score\n            \n        self.active_roster = sorted(scores.keys(), key=lambda x: scores[x], reverse=True)[:self.active_roster_size]\n        print(f\"[PORTFOLIO LOCK] Active Targets: {self.active_roster}\")\n\n    def check_exit_condition(self, ticker, held_tickers, forges):\n        \"\"\"\n        MICRO EXECUTION: Runs every 5 minutes.\n        Determines if an owned asset should be liquidated based on Forge states.\n        \"\"\"\n        current_sig = forges[ticker].get_signal()\n        current_flux = forges[ticker].state.get('H1_Flux', 0)\n        force_exit = False\n        \n        # 1. Standard Exit: The Manifold fractures\n        if current_sig == 'WAIT': \n            force_exit = True\n        else:\n            # 2. The 1.5x Override Exit: A significantly better asset is calling LONG\n            # Find all active roster assets that are LONG but not currently owned\n            cands = [t for t in self.active_roster if forges[t].get_signal() == 'LONG' and t != ticker and t not in held_tickers]\n            \n            if cands:\n                # Find the best candidate using the lighter 10x intraday friction penalty\n                best_alt = max(cands, key=lambda t: forges[t].state.get('H1_Flux', 0) * (1 - (get_friction(t) * 10)))\n                \n                # Trigger the exit ONLY if the alternative is 1.5x better (plus friction variance)\n                if forges[best_alt].state.get('H1_Flux', 0) > (current_flux * (1.5 + (get_friction(best_alt) * 100))):\n                    print(f\"[{ticker}] 1.5x Override Triggered. Making room for {best_alt}.\")\n                    force_exit = True\n                    \n        return force_exit\n"
    },
    {
      "command": "update_file",
      "path": "live/execution/broker_ibkr.py",
      "content": "import asyncio\nimport pytz\nfrom datetime import datetime\nfrom ib_async import IB, Stock, Crypto, LimitOrder\nfrom live.core.math_utils import get_friction\n\nclass IBKRBroker:\n    def __init__(self, max_slots, allocation_per_slot):\n        self.ib = IB()\n        self.max_slots = max_slots\n        self.allocation_per_slot = allocation_per_slot\n        self.est_tz = pytz.timezone('US/Eastern')\n\n    def is_market_open(self):\n        \"\"\"Checks if the US Equity market is currently open (9:31 AM - 4:00 PM EST, Mon-Fri).\"\"\"\n        now_est = datetime.now(self.est_tz)\n        \n        if now_est.weekday() > 4:\n            return False\n            \n        market_open = now_est.replace(hour=9, minute=31, second=0, microsecond=0)\n        market_close = now_est.replace(hour=16, minute=0, second=0, microsecond=0)\n        \n        return market_open <= now_est <= market_close\n\n    async def connect(self, host, port, clientId):\n        \"\"\"Establishes connection to the IB Gateway.\"\"\"\n        await self.ib.connectAsync(host, port, clientId=clientId)\n\n    def disconnect(self):\n        \"\"\"Safely severs the IBKR connection.\"\"\"\n        if self.ib.isConnected():\n            self.ib.disconnect()\n\n    def get_holdings(self):\n        \"\"\"Queries the live IBKR account for current positions and maps them back to our ticker format.\"\"\"\n        positions = self.ib.positions()\n        held_tickers = []\n        for p in positions:\n            if p.position > 0:\n                if p.contract.secType == 'CRYPTO':\n                    held_tickers.append(p.contract.symbol + 'USD')\n                else:\n                    held_tickers.append(p.contract.symbol)\n        return held_tickers\n\n    async def execute(self, ticker, action, price):\n        \"\"\"Builds the IBKR contract, calculates share size, and routes a Marketable Limit Order.\"\"\"\n        is_crypto = 'USD' in ticker\n        \n        # --- MARKET HOURS SAFETY VALVE ---\n        if not is_crypto and not self.is_market_open():\n            print(f\"[{ticker}] 🛑 LIVE {action} BLOCKED: US Equity Market is currently closed or in Opening Cross.\")\n            return False\n        \n        # 1. Map Contract\n        if is_crypto:\n            clean_ticker = ticker.replace('USD', '')\n            contract = Crypto(clean_ticker, 'PAXOS', 'USD')\n        else:\n            contract = Stock(ticker, 'SMART', 'USD')\n            \n        try:\n            await self.ib.qualifyContractsAsync(contract)\n        except Exception as e:\n            print(f\"[{ticker}] LIVE EXECUTION ERROR: Contract qualification failed. ({e})\")\n            return False\n            \n        fric = get_friction(ticker)\n        \n        # 2. Route Action using Marketable Limit Orders\n        if action == 'BUY':\n            if price <= 0:\n                print(f\"[{ticker}] LIVE BUY FAILED: Invalid price (${price}).\")\n                return False\n                \n            usable_capital = self.allocation_per_slot * (1 - fric)\n            shares = round(usable_capital / price, 4)\n            \n            if shares > 0:\n                # Add 0.5% buffer to Tiingo price to guarantee execution\n                limit_price = round(price * 1.005, 2)\n                print(f\"[LIVE IBKR] Routing BUY: {shares} {ticker} @ Limit ${limit_price:.2f} (Tiingo: ${price:.2f})\")\n                \n                order = LimitOrder('BUY', shares, limit_price)\n                order.tif = 'DAY' # Explicitly set TIF to clear the 10349 warning\n                self.ib.placeOrder(contract, order)\n                await asyncio.sleep(1)\n                return True\n            else:\n                print(f\"[{ticker}] LIVE BUY SKIPPED: Capital (${usable_capital:.2f}) insufficient.\")\n                return False\n                \n        elif action == 'SELL':\n            positions = self.ib.positions()\n            shares_owned = round(sum(p.position for p in positions if p.contract.symbol == contract.symbol), 4)\n            \n            if shares_owned > 0:\n                # Subtract 0.5% buffer to Tiingo price to guarantee execution\n                limit_price = round(price * 0.995, 2)\n                print(f\"[LIVE IBKR] Routing SELL: {shares_owned} {ticker} @ Limit ${limit_price:.2f} (Tiingo: ${price:.2f})\")\n                \n                order = LimitOrder('SELL', shares_owned, limit_price)\n                order.tif = 'DAY'\n                self.ib.placeOrder(contract, order)\n                await asyncio.sleep(1)\n                return True\n            else:\n                print(f\"[{ticker}] LIVE SELL SKIPPED: No shares found in IBKR portfolio.\")\n                return False\n                \n        return False\n"
    },
    {
      "command": "update_file",
      "path": "live/execution/broker_sim.py",
      "content": "import pandas as pd\nfrom live.core.math_utils import get_friction\n\nclass SimBroker:\n    def __init__(self, initial_capital, max_slots):\n        self.initial_capital = initial_capital\n        self.cash = initial_capital\n        self.max_slots = max_slots\n        self.allocation_per_slot = self.initial_capital / self.max_slots\n        \n        self.positions = {}\n        self.history = []\n        self.trade_count = 0\n\n    def get_holdings(self):\n        \"\"\"Returns a list of currently owned tickers.\"\"\"\n        return [ticker for ticker, shares in self.positions.items() if shares > 0]\n\n    def get_estimated_portfolio_value(self, current_row):\n        \"\"\"Calculates the real-time mark-to-market value of the simulated portfolio.\"\"\"\n        value = self.cash\n        for ticker, shares in self.positions.items():\n            if shares > 0 and not pd.isna(current_row.get(ticker)):\n                value += shares * current_row[ticker]\n        return value\n\n    async def execute(self, ticker, action, price):\n        \"\"\"Executes the simulated trade with exact backtest friction applied.\"\"\"\n        fric = get_friction(ticker)\n        \n        # Single-slot dynamic compounding allocation update\n        if self.max_slots == 1:\n            self.allocation_per_slot = self.cash\n            \n        if action == 'BUY':\n            usable_capital = self.allocation_per_slot * (1 - fric)\n            shares = round(usable_capital / price, 4)\n            \n            if shares > 0 and self.cash >= (shares * price):\n                self.positions[ticker] = shares\n                cost = shares * price\n                self.cash -= cost\n                self.trade_count += 1\n                self.history.append(f\"BUY {shares} {ticker} @ ${price:.2f} | Fee: {(fric*100):.2f}%\")\n                return True\n            else:\n                return False\n                \n        elif action == 'SELL':\n            shares = self.positions.get(ticker, 0)\n            if shares > 0:\n                revenue = (shares * price) * (1 - fric)\n                self.cash += revenue\n                self.positions[ticker] = 0\n                self.trade_count += 1\n                self.history.append(f\"SELL {shares} {ticker} @ ${price:.2f} | Fee: {(fric*100):.2f}%\")\n                return True\n                \n        return False\n\n    def print_results(self, final_prices):\n        \"\"\"Calculates and displays the final 30-day performance metrics.\"\"\"\n        final_portfolio_value = self.cash\n        \n        for ticker, shares in self.positions.items():\n            if shares > 0 and ticker in final_prices and not pd.isna(final_prices[ticker]):\n                final_portfolio_value += shares * final_prices[ticker]\n                \n        roi = ((final_portfolio_value / self.initial_capital) - 1) * 100\n        \n        print(\"\\n\" + \"=\"*50)\n        print(\"=== 30-DAY WALK-FORWARD SIMULATION RESULTS ===\")\n        print(f\"Starting Capital:  ${self.initial_capital:,.2f}\")\n        print(f\"Ending Capital:    ${final_portfolio_value:,.2f}\")\n        print(f\"Total ROI:         {roi:.2f}%\")\n        print(f\"Total Trades:      {self.trade_count}\")\n        print(\"=\"*50 + \"\\n\")\n"
    },
    {
      "command": "update_file",
      "path": "live/main_live.py",
      "content": "import os\nimport sys\nimport time\nimport asyncio\nimport signal\nimport pytz\nimport pandas as pd\nfrom datetime import datetime, timedelta\n\n# Ensure python can resolve the 'live' module\nsys.path.append(os.path.dirname(os.path.dirname(os.path.abspath(__file__))))\n\nfrom live.core.master_controller_V2 import LiveGatedForge\nfrom live.core.portfolio_manager import PortfolioManager\nfrom live.data_code.cache_manager import DataCacheManager\nfrom live.execution.broker_sim import SimBroker\nfrom live.execution.broker_ibkr import IBKRBroker\n\n# === CONFIG ===\nTIINGO_TOKEN = '1e1b9c4ef14bdc6ad07d14b6d5d8563c447ecbe3' \nVIRTUAL_CAPITAL_USD = 3250.00\nMAX_SLOTS = 1\nALLOCATION_PER_SLOT = VIRTUAL_CAPITAL_USD / MAX_SLOTS\nASSETS = [\n    'NVDA', 'MSFT', 'AVGO', 'AAPL', 'AMZN', 'MSTR', 'COIN', 'PLTR', 'CRWD', 'TSLA', \n    'V', 'META', 'CAT', 'NEE', 'CBOE', 'NEM', 'PAAS', 'FCX', 'XOM', 'CCJ',\n    'WMT', 'LLY', 'JPM', 'btcusd', 'ethusd', 'solusd', 'avaxusd', 'dogeusd', 'adausd', 'dotusd'\n]\n\n# --- GLOBAL SHUTDOWN FLAG ---\nis_shutting_down = False\n\ndef handle_exit(sig, frame):\n    \"\"\"Ensures IBKR connection is torn down cleanly on Ctrl+C.\"\"\"\n    global is_shutting_down\n    is_shutting_down = True\n    print(\"\\n[SYSTEM] Shutdown signal received. Disconnecting...\")\n    sys.exit(0)\n\nsignal.signal(signal.SIGINT, handle_exit)\n\ndef is_equity_open(dt_naive):\n    \"\"\"Checks if a local naive datetime corresponds to active US Equity Market hours.\"\"\"\n    try:\n        local_tz = datetime.now().astimezone().tzinfo\n        aware_dt = dt_naive.replace(tzinfo=local_tz)\n        est_dt = aware_dt.astimezone(pytz.timezone('US/Eastern'))\n        if est_dt.weekday() > 4: return False\n        if est_dt.hour < 9 or (est_dt.hour == 9 and est_dt.minute < 30): return False\n        if est_dt.hour >= 16: return False\n        return True\n    except Exception:\n        return True\n\nasync def connect_with_retry(broker, host='127.0.0.1', port=4002):\n    for cid in range(1, 11):\n        try:\n            print(f\"[IBKR] Attempting connection (ClientID: {cid})...\")\n            if hasattr(broker, 'ib') and broker.ib.isConnected():\n                broker.ib.disconnect()\n            \n            await broker.connect(host, port, clientId=cid)\n            print(f\"✅ [IBKR] Connected successfully (ID: {cid})\")\n            return True\n        except Exception as e:\n            if \"already in use\" in str(e) or \"326\" in str(e) or \"Timeout\" in str(e):\n                print(f\"⚠️ [IBKR] ClientID {cid} is busy or timed out, rotating...\")\n                continue\n            else:\n                print(f\"❌ [IBKR] Unexpected Connection Error: {e}\")\n                break\n    return False\n\ndef log_telemetry(file_path, timestamp, ticker, price, signal, forge):\n    state = forge.state\n    with open(file_path, 'a') as f:\n        f.write(f\"{timestamp},{ticker},{price},{signal},{state.get('H1_Flux',0)},{state.get('M5_Flux',0)},{state.get('M5_Rds',0)}\\n\")\n\nasync def run_unified_engine():\n    print(\"\\n=== INITIALIZING UNIFIED GATED FORGE ORCHESTRATOR ===\")\n    \n    cache = DataCacheManager(ASSETS, TIINGO_TOKEN)\n    portfolio = PortfolioManager(ASSETS, active_roster_size=5)\n    forges = {ticker: LiveGatedForge(ticker) for ticker in ASSETS}\n    \n    telemetry_file = os.path.join(cache.data_dir, 'telemetry.csv')\n    with open(telemetry_file, 'w') as f:\n        f.write(\"timestamp,ticker,price,signal,h1_flux,m5_state,m5_rds\\n\")\n    \n    m5_timeline = cache.sync_and_load_history()\n    sim_broker = SimBroker(VIRTUAL_CAPITAL_USD, MAX_SLOTS)\n    warmup_end_time = m5_timeline.index[0] + timedelta(days=30) \n    \n    last_h1_hour = -1\n    last_quarter_week = -1\n    last_draft_week = -1\n    last_print_day = -1\n    \n    sim_entry_prices = {} \n    \n    print(f\"\\n[PHASE 1/2] Simulating + Hydrating Telemetry...\")\n    \n    for current_time, row in m5_timeline.iterrows():\n        current_week = current_time.isocalendar()[1]\n        market_open_now = is_equity_open(current_time)\n        \n        if current_time.day != last_print_day:\n            last_print_day = current_time.day\n            if current_time <= warmup_end_time:\n                print(f\"  -> Warming Up: {current_time.strftime('%Y-%m-%d')}\")\n            else:\n                current_pnl = sim_broker.get_estimated_portfolio_value(row)\n                print(f\"\\n  -> Simulating: {current_time.strftime('%Y-%m-%d')} | Est. Portfolio: ${current_pnl:,.2f}\")\n\n        if not portfolio.golden_list or (current_week % 13 == 0 and current_week != last_quarter_week):\n            portfolio.rebuild_golden_list(current_time, cache.daily_master)\n            last_quarter_week = current_week\n        if not portfolio.active_roster or current_week != last_draft_week:\n            portfolio.rebuild_active_roster(current_time, cache.daily_master)\n            last_draft_week = current_week\n\n        is_h1_close = current_time.hour != last_h1_hour\n        if is_h1_close: last_h1_hour = current_time.hour\n        \n        for ticker in ASSETS:\n            price = row[ticker]\n            if not pd.isna(price):\n                is_crypto = 'usd' in ticker.lower()\n                \n                # --- DATA INGESTION GUARD ---\n                # Freeze physics for sleeping equities to prevent volatility decay\n                if not is_crypto and not market_open_now:\n                    pass\n                else:\n                    if is_h1_close: forges[ticker].ingest_h1(price)\n                    forges[ticker].ingest_m5(price)\n\n        if current_time <= warmup_end_time: continue\n\n        held_tickers = sim_broker.get_holdings()\n        active_roster = portfolio.active_roster\n        \n        for ticker in active_roster:\n            if ticker in row and not pd.isna(row[ticker]):\n                log_telemetry(telemetry_file, current_time, ticker, row[ticker], forges[ticker].get_signal(), forges[ticker])\n\n        for ticker in list(held_tickers):\n            is_roster_drop = ticker not in active_roster\n            force_exit = False if is_roster_drop else portfolio.check_exit_condition(ticker, held_tickers, forges)\n            \n            if is_roster_drop or force_exit:\n                price = row.get(ticker, 0)\n                if await sim_broker.execute(ticker, 'SELL', price):\n                    held_tickers.remove(ticker)\n                    \n                    if is_roster_drop:\n                        reason = \"Roster Drop\"\n                    elif forges[ticker].get_signal() == 'WAIT':\n                        reason = \"Signal WAIT\"\n                    else:\n                        reason = \"1.5x Override\"\n                        \n                    entry_p = sim_entry_prices.get(ticker, price)\n                    pnl_pct = ((price - entry_p) / entry_p * 100) if entry_p > 0 else 0.0\n                    \n                    state = forges[ticker].state\n                    flux = state.get('H1_Flux', 0)\n                    \n                    print(f\"    [SIM SELL] {ticker:<5} | PnL: {pnl_pct:>+6.2f}% | Reason: {reason:<14} | Exit Flux: {flux:.2f}\")\n\n        for ticker in active_roster:\n            if ticker not in held_tickers and len(held_tickers) < MAX_SLOTS:\n                if forges[ticker].get_signal() == 'LONG' and not pd.isna(row.get(ticker)):\n                    price = row[ticker]\n                    if await sim_broker.execute(ticker, 'BUY', price):\n                        held_tickers.append(ticker)\n                        sim_entry_prices[ticker] = price\n                        \n                        state = forges[ticker].state\n                        flux = state.get('H1_Flux', 0)\n                        ceil = state.get('Ceiling', 0)\n                        rds = state.get('M5_Rds', 0)\n                        tilt = state.get('H1_Tilt', 0)\n                        \n                        print(f\"    [SIM BUY]  {ticker:<5} | Flux: {flux:>5.2f}/{ceil:<5.2f} | Rds: {rds:.4f} | Tilt: {tilt:.4f}\")\n                    \n    sim_broker.print_results(m5_timeline.iloc[-1])\n    \n    print(\"\\n[PHASE 3] Live Execution Armed.\")\n    \n    live_broker = IBKRBroker(MAX_SLOTS, ALLOCATION_PER_SLOT)\n    connected = await connect_with_retry(live_broker, host='127.0.0.1', port=4002)\n    \n    if not connected:\n        print(\"❌ [FATAL] IBKR Connect Failed after 10 attempts. Exiting.\")\n        return\n        \n    try:\n        while not is_shutting_down:\n            now = datetime.now()\n            sleep_seconds = (300 - (now.minute % 5) * 60 - now.second) + 15\n            print(f\"\\n[LIVE] Next Tick in {sleep_seconds}s...\")\n            await asyncio.sleep(max(sleep_seconds, 5))\n            \n            if is_shutting_down: break\n            \n            current_time = datetime.now()\n            current_prices = cache.fetch_live_tick()\n            market_open_now = is_equity_open(current_time)\n            \n            if not current_prices:\n                print(\"⚠️ [WARN] Empty live fetch. Waiting for next cycle.\")\n                continue\n\n            held_tickers = live_broker.get_holdings()\n            active_roster = portfolio.active_roster\n            print(f\"\\n=== ⚡ LIVE TICK: {current_time.strftime('%H:%M:%S')} ===\")\n            print(f\"📦 Holdings: {held_tickers if held_tickers else 'NONE'} | 🎯 Roster: {active_roster}\")\n\n            is_h1_close = current_time.hour != last_h1_hour\n            if is_h1_close: last_h1_hour = current_time.hour\n            \n            for ticker, price in current_prices.items():\n                is_crypto = 'usd' in ticker.lower()\n                \n                # --- DATA INGESTION GUARD ---\n                # Freeze physics for sleeping equities to prevent volatility decay\n                if not is_crypto and not market_open_now:\n                    pass\n                else:\n                    if is_h1_close: forges[ticker].ingest_h1(price)\n                    forges[ticker].ingest_m5(price)\n                    \n                if ticker in portfolio.active_roster:\n                    log_telemetry(telemetry_file, current_time, ticker, price, forges[ticker].get_signal(), forges[ticker])\n\n            current_week = current_time.isocalendar()[1]\n            if current_week % 13 == 0 and current_week != last_quarter_week:\n                print(f\"\\n[LIVE] Triggering Quarterly Golden List Rebuild...\")\n                portfolio.rebuild_golden_list(current_time, cache.daily_master)\n                last_quarter_week = current_week\n                \n            if current_week != last_draft_week:\n                print(f\"\\n[LIVE] Triggering Weekly Active Roster Draft...\")\n                portfolio.rebuild_active_roster(current_time, cache.daily_master)\n                last_draft_week = current_week\n\n            try:\n                for ticker in list(held_tickers):\n                    if ticker not in active_roster or portfolio.check_exit_condition(ticker, held_tickers, forges):\n                        price = current_prices.get(ticker, 0)\n                        if price > 0:\n                            print(f\"[LIVE] Exit condition met for {ticker}. Executing SELL.\")\n                            success = await live_broker.execute(ticker, 'SELL', price)\n                            if success: held_tickers.remove(ticker)\n\n                for ticker in active_roster:\n                    if ticker not in held_tickers and len(held_tickers) < MAX_SLOTS:\n                        signal = forges[ticker].get_signal()\n                        price = current_prices.get(ticker, 0)\n                        \n                        if signal == 'LONG' and price > 0:\n                            print(f\"[LIVE] Entry condition met for {ticker} (LONG). Executing BUY.\")\n                            success = await live_broker.execute(ticker, 'BUY', price)\n                            if success: held_tickers.append(ticker)\n            except Exception as execution_error:\n                print(f\"❌ [LIVE EXECUTION ERROR] {execution_error}\")\n\n    except asyncio.CancelledError:\n        pass\n    except Exception as e:\n        print(f\"\\n❌ [RUNTIME ERROR] {e}\")\n    finally:\n        print(\"\\n[SYSTEM] Tearing down IBKR connection...\")\n        if hasattr(live_broker, 'ib') and live_broker.ib.isConnected():\n            live_broker.ib.disconnect()\n\nif __name__ == '__main__':\n    if sys.platform == 'win32':\n        asyncio.set_event_loop_policy(asyncio.WindowsSelectorEventLoopPolicy())\n    try: \n        asyncio.run(run_unified_engine())\n    except KeyboardInterrupt: \n        pass\n"
    }
  ]
}